com/__init__.py
com/baseus/__init__.py
com/baseus/detect/__init__.py
com/baseus/detect/test.py
yolov8_detect-1.1.dist-info/METADATA
yolov8_detect-1.1.dist-info/WHEEL
yolov8_detect-1.1.dist-info/top_level.txt
yolov8_detect-1.1.dist-info/RECORD
