Metadata-Version: 2.1
Name: yolov8-detect
Version: 1.1
Summary: offer the datasets can tran the new model,offer the model and image can infer the object in the image
Home-page: UNKNOWN
Author: xingyue
Author-email: ywb10.8@qq.com
License: UNKNOWN
Platform: UNKNOWN
Requires-Dist: numpy
